isoformevent/__init__.py
isoformevent/creategenes.py
isoformevent/drawgene.py
isoformevent/gene.py
isoformevent/readgene.py
isoformevent/savegene.py
isoformevent/transcript.py
isoformevent-0.0.1.dist-info/METADATA
isoformevent-0.0.1.dist-info/WHEEL
isoformevent-0.0.1.dist-info/top_level.txt
isoformevent-0.0.1.dist-info/RECORD
