Metadata-Version: 2.1
Name: isoformevent
Version: 0.0.1
Summary: Protein Isoform Event identifier
Author: Julian Perez
Author-email: <julian.perez@stanford.edu>
License: UNKNOWN
Keywords: python,protein,isoform,event
Platform: UNKNOWN
Classifier: Development Status :: 3 - Alpha
Classifier: Intended Audience :: Education
Classifier: Programming Language :: Python :: 2
Classifier: Programming Language :: Python :: 3
Classifier: Operating System :: MacOS :: MacOS X
Classifier: Operating System :: Microsoft :: Windows
Requires-Dist: pandas
Requires-Dist: numpy
Requires-Dist: os
Requires-Dist: pickle
Requires-Dist: matplotlib
